Workbook
Name aporte: Planilha1!$D$23:$D$23
Name patrimonio: Planilha1!$D$26:$D$26
Name qtd_anos: Planilha1!$D$24:$D$24
Name rendimento_carteira: Planilha1!$D$19:$D$19
Name salario: Planilha1!$D$18:$D$18
Name sugetao_investimento: Planilha1!$D$20:$D$20
Name taxa_mensal: Planilha1!$D$25:$D$25

Sheet Planilha1
C15: Calculadora de Investimentos IN-BEST
C17: Configurações
C18: Salário | D18: 2500
C19: Rendimento da Carteira | D19: 0.01
C20: Sugestão de Investimento (30%) | D20: {=salario*0.3} -> 750
C22: Investimento Mensal
C23: Quanto investir Por Mês? | D23: 700
C24: Por quantos anos? | D24: 2
C25: Qual A Taxa De Rendimento Mensal? | D25: 0.01
C26: O Patrimônio Acumulado Será De | D26: {=FV(taxa_mensal,qtd_anos*12,aporte*-1)} -> 18881.425
C27: Dividendos Mensais | D27: {=patrimonio*D19} -> 188.81425
C29: Cenários | E29: Dividendos
C30: Quanto Renderá Em 2 Anos? | D30: =FV($D$25,$I33*12,$D$23*-1) -> 18881.425 | E30: =D30*$D$19 -> 188.81425
C31: Quanto Renderá Em 5 Anos? | D31: =FV($D$25,$I34*12,$D$23*-1) -> 57168.769 | E31: =D31*$D$19 -> 571.68769
C32: Quanto Renderá Em 10 Anos? | D32: =FV($D$25,$I35*12,$D$23*-1) -> 161027.08 | E32: =D32*$D$19 -> 1610.2708
C33: Quanto Renderá Em 20 Anos? | D33: =FV($D$25,$I46*12,$D$23*-1) -> 692478.76 | E33: =D33*$D$19 -> 6924.7876 | I33: 2
C34: Quanto Renderá Em 30 Anos? | D34: =FV($D$25,$I65*12,$D$23*-1) -> 2446474.9 | E34: =D34*$D$19 -> 24464.749 | I34: 5
I35: 10
C36: Perfil | D36: Agressivo
C37: Valor A Ser Investido Por Mês | D37: =D23 -> 700
C39: Tipo de FII | D39: Percentual Sugerido | E39: Valores
C40: Papel | D40: =VLOOKUP($D$36&"-"&C40,Planilha2!B2:E20,4,FALSE) -> 0.5 | E40: =$D$37*D40 -> 350
C41: Tijolo | D41: =VLOOKUP($D$36&"-"&C41,Planilha2!B3:E21,4,FALSE) -> 0.1 | E41: =$D$37*D41 -> 70
C42: Híbridos | D42: =VLOOKUP($D$36&"-"&C42,Planilha2!B4:E22,4,FALSE) -> 0.05 | E42: =$D$37*D42 -> 35
C43: FOFs | D43: =VLOOKUP($D$36&"-"&C43,Planilha2!B5:E23,4,FALSE) -> 0.05 | E43: =$D$37*D43 -> 35
C44: Desenvolvimento | D44: =VLOOKUP($D$36&"-"&C44,Planilha2!B6:E24,4,FALSE) -> 0.2 | E44: =$D$37*D44 -> 140
C45: Hotelarias | D45: =VLOOKUP($D$36&"-"&C45,Planilha2!B7:E25,4,FALSE) -> 0.1 | E45: =$D$37*D45 -> 70
C46: Total | D46: =SUM(E40:E45) -> 700 | I46: 20
I65: 30

Sheet Planilha2
B2: chave | C2: Perfil | D2: Tipo de FII | E2: Porcentagem
B3: =$C$3&"-"&D3 -> Conservador-Papel | C3: Conservador | D3: Papel | E3: 0.3
B4: =$C$3&"-"&D4 -> Conservador-Tijolo | C4: Conservador | D4: Tijolo | E4: 0.5
B5: =$C$3&"-"&D5 -> Conservador-Híbridos | C5: Conservador | D5: Híbridos | E5: 0.1 | I5: Moderado-Tijolo | J5: =VLOOKUP(B10,B2:E20,4,FALSE) -> 0.35
B6: =$C$3&"-"&D6 -> Conservador-FOFs | C6: Conservador | D6: FOFs | E6: 0.1
B7: =$C$3&"-"&D7 -> Conservador-Desenvolvimento | C7: Conservador | D7: Desenvolvimento | E7: 0
B8: =$C$3&"-"&D8 -> Conservador-Hotelarias | C8: Conservador | D8: Hotelarias | E8: 0
B9: =$C$9&"-"&D9 -> Moderado-Papel | C9: Moderado | D9: Papel | E9: 0.32
B10: =$C$9&"-"&D10 -> Moderado-Tijolo | C10: Moderado | D10: Tijolo | E10: 0.35
B11: =$C$9&"-"&D11 -> Moderado-Híbridos | C11: Moderado | D11: Híbridos | E11: 0.8
B12: =$C$9&"-"&D12 -> Moderado-FOFs | C12: Moderado | D12: FOFs | E12: 0.05
B13: =$C$9&"-"&D13 -> Moderado-Desenvolvimento | C13: Moderado | D13: Desenvolvimento | E13: 0.1
B14: =$C$9&"-"&D14 -> Moderado-Hotelarias | C14: Moderado | D14: Hotelarias | E14: 0.1
B15: =C15&"-"&D15 -> Agressivo-Papel | C15: Agressivo | D15: Papel | E15: 0.5
B16: =C16&"-"&D16 -> Agressivo-Tijolo | C16: Agressivo | D16: Tijolo | E16: 0.1
B17: =C17&"-"&D17 -> Agressivo-Híbridos | C17: Agressivo | D17: Híbridos | E17: 0.05
B18: =C18&"-"&D18 -> Agressivo-FOFs | C18: Agressivo | D18: FOFs | E18: 0.05
B19: =C19&"-"&D19 -> Agressivo-Desenvolvimento | C19: Agressivo | D19: Desenvolvimento | E19: 0.2
B20: =C20&"-"&D20 -> Agressivo-Hotelarias | C20: Agressivo | D20: Hotelarias | E20: 0.1
